niphlem/__init__.py
niphlem/clean.py
niphlem/events.py
niphlem/input_data.py
niphlem/models.py
niphlem/report/__init__.py
niphlem/report/ecg_report.py
niphlem/report/html_report.py
niphlem/report/pulse_report.py
niphlem/report/report_body_ecg.html
niphlem/report/report_body_pulse.html
niphlem/report/report_body_resp.html
niphlem/report/report_general.py
niphlem/report/report_head.html
niphlem/report/resp_report.py
niphlem-0.0.3.dist-info/LICENSE
niphlem-0.0.3.dist-info/METADATA
niphlem-0.0.3.dist-info/WHEEL
niphlem-0.0.3.dist-info/top_level.txt
niphlem-0.0.3.dist-info/RECORD
