Metadata-Version: 2.1
Name: niphlem
Version: 0.0.3
Summary: Physiological Log Extraction for Modelling in Neuroimaging
Home-page: https://github.com/CoAxLab/niphlem
License: UNKNOWN
Project-URL: Bug Tracker, https://github.com/CoAxLab/niphlem/issues
Platform: UNKNOWN
Classifier: Programming Language :: Python :: 3
Classifier: License :: OSI Approved :: BSD License
Classifier: Operating System :: OS Independent
Requires-Python: >=3.6
License-File: LICENSE
Requires-Dist: numpy
Requires-Dist: matplotlib
Requires-Dist: pandas
Requires-Dist: scipy
Requires-Dist: scikit-learn
Requires-Dist: outlier-utils
